viberandom/__init__.py
viberandom/ai.py
viberandom/py.typed
viberandom-0.1.0.dist-info/METADATA
viberandom-0.1.0.dist-info/WHEEL
viberandom-0.1.0.dist-info/licenses/LICENSE
viberandom-0.1.0.dist-info/RECORD
