Metadata-Version: 2.4
Name: viberandom
Version: 0.1.0
Summary: Random number generation library that uses Gemini to generate numbers with vibes
Author-email: jeantimex <jean.timex@gmail.com>
License-File: LICENSE
Requires-Python: >=3.10
Requires-Dist: google-generativeai>=0.8.0
Requires-Dist: pydantic>=2.11.7
Requires-Dist: typing-extensions>=4.14.1
